snakemake/__init__.py
snakemake/__main__.py
snakemake/_version.py
snakemake/api.py
snakemake/benchmark.py
snakemake/checkpoints.py
snakemake/cli.py
snakemake/cwl.py
snakemake/dag.py
snakemake/decorators.py
snakemake/exceptions.py
snakemake/gui.html
snakemake/gui.py
snakemake/ioflags.py
snakemake/jobs.py
snakemake/logging.py
snakemake/modules.py
snakemake/notebook.py
snakemake/output_index.py
snakemake/parser.py
snakemake/path_modifier.py
snakemake/pathvars.py
snakemake/persistence.py
snakemake/persistence_encryption.py
snakemake/profiles.py
snakemake/report.css
snakemake/resources.py
snakemake/ruleinfo.py
snakemake/rules.py
snakemake/shell.py
snakemake/sourcecache.py
snakemake/spawn_jobs.py
snakemake/storage.py
snakemake/target_jobs.py
snakemake/utils.py
snakemake/workflow.py
snakemake/wrapper.py
snakemake/assets/__init__.py
snakemake/caching/__init__.py
snakemake/caching/hash.py
snakemake/caching/local.py
snakemake/caching/storage.py
snakemake/common/__init__.py
snakemake/common/argparse.py
snakemake/common/configfile.py
snakemake/common/git.py
snakemake/common/prefix_lookup.py
snakemake/common/tbdstring.py
snakemake/common/typing.py
snakemake/common/workdir_handler.py
snakemake/common/tests/__init__.py
snakemake/common/tests/testcases/__init__.py
snakemake/common/tests/testcases/groups/__init__.py
snakemake/common/tests/testcases/simple/__init__.py
snakemake/deployment/__init__.py
snakemake/deployment/conda.py
snakemake/deployment/containerize.py
snakemake/deployment/env_modules.py
snakemake/deployment/singularity.py
snakemake/executors/__init__.py
snakemake/executors/dryrun.py
snakemake/executors/google_lifesciences_helper.py
snakemake/executors/local.py
snakemake/executors/touch.py
snakemake/io/__init__.py
snakemake/io/fmt.py
snakemake/io/flags/__init__.py
snakemake/io/flags/access_patterns.py
snakemake/ioutils/__init__.py
snakemake/ioutils/branch.py
snakemake/ioutils/collect.py
snakemake/ioutils/evaluate.py
snakemake/ioutils/exists.py
snakemake_without_snakefile-2025.11.13.dist-info/licenses/LICENSE
snakemake_without_snakefile-2025.11.13.dist-info/METADATA
snakemake_without_snakefile-2025.11.13.dist-info/WHEEL
snakemake_without_snakefile-2025.11.13.dist-info/entry_points.txt
snakemake_without_snakefile-2025.11.13.dist-info/top_level.txt
snakemake_without_snakefile-2025.11.13.dist-info/RECORD
