Metadata-Version: 2.4
Name: snakemake_without_snakefile
Version: 2025.11.13
Summary: Modified Snakemake library that supports defining workflows via strings without Snakefile
Author-email: Johannes Köster <johannes.koester@uni-due.de>, DeeliN221 <DeeliN221zzl@gmail.com>
License-Expression: MIT
Keywords: workflow,pipeline,bioinformatics
Classifier: Development Status :: 5 - Production/Stable
Classifier: Environment :: Console
Classifier: Intended Audience :: Science/Research
Classifier: Natural Language :: English
Classifier: Programming Language :: Python :: 3.11
Classifier: Programming Language :: Python :: 3.12
Classifier: Programming Language :: Python :: 3.13
Classifier: Topic :: Scientific/Engineering :: Bio-Informatics
Requires-Python: >=3.11
License-File: LICENSE
Requires-Dist: appdirs
Requires-Dist: immutables
Requires-Dist: configargparse
Requires-Dist: connection_pool>=0.0.3
Requires-Dist: docutils
Requires-Dist: gitpython
Requires-Dist: humanfriendly
Requires-Dist: jinja2<4.0,>=3.0
Requires-Dist: jsonschema
Requires-Dist: nbformat
Requires-Dist: packaging>=24.0
Requires-Dist: psutil
Requires-Dist: pulp<3.4,>=2.3.1
Requires-Dist: pyyaml
Requires-Dist: referencing
Requires-Dist: requests<3.0,>=2.8.1
Requires-Dist: reretry
Requires-Dist: smart-open<8.0,>=4.0
Requires-Dist: snakemake-interface-executor-plugins<10.0,>=9.3.2
Requires-Dist: snakemake-interface-common<2.0,>=1.20.1
Requires-Dist: snakemake-interface-storage-plugins<5.0,>=4.1.0
Requires-Dist: snakemake-interface-report-plugins<2.0.0,>=1.2.0
Requires-Dist: snakemake-interface-logger-plugins<3.0.0,>=1.1.0
Requires-Dist: snakemake-interface-scheduler-plugins<3.0.0,>=2.0.0
Requires-Dist: tabulate
Requires-Dist: throttler
Requires-Dist: wrapt
Requires-Dist: yte<2.0,>=1.5.5
Requires-Dist: dpath<3.0.0,>=2.1.6
Requires-Dist: conda-inject<2.0,>=1.3.1
Dynamic: license-file
